pyppeteer_pdf/__init__.py
pyppeteer_pdf/cli.py
pyppeteer_pdf-0.1.2.dist-info/entry_points.txt
pyppeteer_pdf-0.1.2.dist-info/WHEEL
pyppeteer_pdf-0.1.2.dist-info/METADATA
pyppeteer_pdf-0.1.2.dist-info/RECORD
